certbot_dns_openstack/__init__.py
certbot_dns_openstack/dns_openstack.py
certbot_dns_openstack/tests/__init__.py
certbot_dns_openstack/tests/base.py
certbot_dns_openstack/tests/test_certbot_dns_openstack.py
certbot_dns_openstack-0.0.1.dist-info/METADATA
certbot_dns_openstack-0.0.1.dist-info/RECORD
certbot_dns_openstack-0.0.1.dist-info/WHEEL
certbot_dns_openstack-0.0.1.dist-info/entry_points.txt
certbot_dns_openstack-0.0.1.dist-info/pbr.json
certbot_dns_openstack-0.0.1.dist-info/top_level.txt
